FigureForge/__init__.py
FigureForge/dialogs/about_dialog.py
FigureForge/dialogs/bug_report_dialog.py
FigureForge/dialogs/export_figure_dialog.py
FigureForge/dialogs/ff_dialogs.py
FigureForge/dialogs/new_plugin_dialog.py
FigureForge/dialogs/save_work_dialog.py
FigureForge/dialogs/update_check.py
FigureForge/dialogs/welcome_dialog.py
FigureForge/figure_explorer.py
FigureForge/figure_manager.py
FigureForge/gui.py
FigureForge/main.py
FigureForge/plugins/__init__.py
FigureForge/plugins/add_annotation.png
FigureForge/plugins/add_annotation.py
FigureForge/plugins/add_legend.png
FigureForge/plugins/add_legend.py
FigureForge/plugins/add_minor_data_ticks.png
FigureForge/plugins/add_minor_data_ticks.py
FigureForge/plugins/plugin_requirements.txt
FigureForge/plugins/reduce_tick_limits.png
FigureForge/plugins/reduce_tick_limits.py
FigureForge/plugins/set_spine_bounds.png
FigureForge/plugins/set_spine_bounds.py
FigureForge/plugins/toggle_spines.png
FigureForge/plugins/toggle_spines.py
FigureForge/plugins/utils/add_annotations_dialog.py
FigureForge/plugins/utils/add_legend_dialog.py
FigureForge/plugins/utils/color_button.py
FigureForge/plugins/utils/custom_spinbox.py
FigureForge/plugins/utils/select_spines_dialog.py
FigureForge/preferences.py
FigureForge/property_inspector.py
FigureForge/resources/assets/demo.png
FigureForge/resources/assets/logo.ico
FigureForge/resources/assets/logo_256.png
FigureForge/resources/assets/logo_bw_notext.png
FigureForge/resources/assets/logo_bw_notext.svg
FigureForge/resources/assets/logo_bw_text.png
FigureForge/resources/assets/logo_bw_text.svg
FigureForge/resources/assets/logo_color_notext.ico
FigureForge/resources/assets/logo_color_notext.png
FigureForge/resources/assets/logo_color_notext.svg
FigureForge/resources/assets/logo_color_text.png
FigureForge/resources/assets/logo_color_text.svg
FigureForge/resources/assets/splash.png
FigureForge/resources/icons/about_icon.png
FigureForge/resources/icons/add_axes_icon.png
figureforge-0.3.3.dist-info/LICENSE
figureforge-0.3.3.dist-info/METADATA
figureforge-0.3.3.dist-info/WHEEL
figureforge-0.3.3.dist-info/entry_points.txt
figureforge-0.3.3.dist-info/RECORD
