Metadata-Version: 2.3
Name: FigureForge
Version: 0.3.3
Summary: 
License: MIT
Author: Noah Gula
Author-email: noahrgula@gmail.com
Requires-Python: >=3.11,<3.14
Classifier: License :: OSI Approved :: MIT License
Classifier: Programming Language :: Python :: 3
Classifier: Programming Language :: Python :: 3.11
Classifier: Programming Language :: Python :: 3.12
Classifier: Programming Language :: Python :: 3.13
Requires-Dist: PySide6 (>=6.7.2,<7.0.0)
Requires-Dist: appdirs (>=1.4.4,<2.0.0)
Requires-Dist: importlib (>=1.0.4,<2.0.0)
Requires-Dist: matplotlib (>=3.9.1,<4.0.0)
Requires-Dist: numpy (>=1.26.0,<2.0.0)
Requires-Dist: pyqtdarktheme-fork (>=2.3.4,<3.0.0)
Requires-Dist: requests (>=2.26.0,<3.0.0)
